exelog.py
exelog-0.0.1.dist-info/LICENSE
exelog-0.0.1.dist-info/METADATA
exelog-0.0.1.dist-info/WHEEL
exelog-0.0.1.dist-info/top_level.txt
exelog-0.0.1.dist-info/RECORD
