Metadata-Version: 2.1
Name: exelog
Version: 0.0.1
Summary: Enabling meticulous logging for Spark Applications
Home-page: https://github.com/Spratiher9/Exelog
Author: Souvik Pratiher
Author-email: spratiher9@gmail.com
License: UNKNOWN
Platform: UNKNOWN
Classifier: Development Status :: 5 - Production/Stable
Classifier: Programming Language :: Python :: 3
Classifier: License :: OSI Approved :: Apache Software License
Classifier: Operating System :: OS Independent
Requires-Python: >=3.5
License-File: LICENSE
Requires-Dist: atomicwrites
Requires-Dist: attrs
Requires-Dist: colorama
Requires-Dist: iniconfig
Requires-Dist: packaging
Requires-Dist: pluggy
Requires-Dist: py
Requires-Dist: py4j
Requires-Dist: pyparsing
Requires-Dist: pyspark
Requires-Dist: pytest
Requires-Dist: toml
